pjt/__init__.py
pjt/app.py
pjt/cli/__init__.py
pjt/cli/application.py
pjt/cli/commands.py
pjt/core/__init__.py
pjt/core/entities.py
pjt/core/pypi.py
pjt/py.typed
pip_jump_to-0.1.0.dist-info/entry_points.txt
pip_jump_to-0.1.0.dist-info/METADATA
pip_jump_to-0.1.0.dist-info/LICENSE
pip_jump_to-0.1.0.dist-info/WHEEL
pip_jump_to-0.1.0.dist-info/RECORD
